{"00牧_勤劳牧场主(星宇)":{"00 查看->领取":{"Url":"nc.qzone.qq.com/cgi-bin/query","Post":"{mcs}&act=2191001","Note":"2021.08.01-2021.08.27","Msg":"direction;num#积分&&daynum#当天得分","MsgOut":"num#积分&&daynum#当天得分","End":"登;不;+"},"01 免费积分奖励一键领取":{"Url":"nc.qzone.qq.com/cgi-bin/exchange","Post":"{mcs}&act=2191003&type=1&id=0","Note":"id= 1~28   需累计积分 12~~672\r\nid=0   一键领取","Msg":"direction;pkg??","MsgOut":"direction;pkg??","End":"登;不;没;才;异常{02}"},"02 进入游戏":{"Url":"{!mc}cgi_pasture_sprite_move","Post":"{mcs}","Msg":"direction;ecode","MsgOut":"direction;ecode","End":"0{01}"}}}