{"00农_制作礼品袜(星宇)":{"00 查看->领取":{"Url":"nc.qzone.qq.com/cgi-bin/query","Post":"{ncs}&act=2028001","Note":"2021.12.23-2021.12.30","Msg":"direction;vt1993#普袜&&vt1994#中袜&&vt1995#高袜&&vt1996#VIP高袜l_jf#积分&&l_times#已点","MsgOut":"direction;vt1993#普袜&&vt1994#中袜&&vt1995#高袜&&vt1996#VIP高袜l_jf#积分&&l_times#已点","End":"登;不;+","Task":20},"01 VIP":{"Url":"nc.qzone.qq.com/cgi-bin/exchange","Post":"{ncs}&act=2028005&id={*:1,2}","Msg":"direction;pkg??","MsgOut":"direction;pkg??","Task":20},"02 制作普":{"Url":"nc.qzone.qq.com/cgi-bin/exchange","Post":"{ncs}&act=2028002&id=1","Msg":"direction;pkg??","MsgOut":"direction;pkg??","End":"登;不","Cycle":-1,"Task":20},"03 制作中":{"Url":"nc.qzone.qq.com/cgi-bin/exchange","Post":"{ncs}&act=2028002&id=2","Msg":"direction;pkg??","MsgOut":"direction;pkg??","End":"登;不","Cycle":-1,"Task":13},"04 制作高":{"Url":"nc.qzone.qq.com/cgi-bin/exchange","Post":"{ncs}&act=2028002&id=3","Msg":"direction;pkg??","MsgOut":"direction;pkg??","End":"登;不","Cycle":-1,"Task":13},"05 兑换礼包":{"Url":"nc.qzone.qq.com/cgi-bin/exchange","Post":"{ncs}&act=2028004&id=4","Note":"id=1~4 需积分 60/90/124/230","Msg":"direction;pkg??","MsgOut":"direction;pkg??","End":"登;不","Task":20},"06 当天累积次数礼包":{"Url":"nc.qzone.qq.com/cgi-bin/exchange","Post":"{ncs}&act=2028003&id={*:1~3}","Note":"id=1~3  \r\n当天累积制作次数 10/15/25","Msg":"direction;pkg??","MsgOut":"direction;pkg??","End":"登","Task":20}}}