{"00农_丰收好礼乐翻天":{"00查看+收获【每天】":{"Url":"{!nc}query","Post":"{ncs}&act=2103001","Note":"2021.04.29-2021.05.06","Msg":"l_jf#积分&&vt1871#次数&&l_52730#小麦&&l_52731#玉米&&l_52732#花生","MsgOut":"l_jf#积分&&vt1871#次数&&l_52730#小麦&&l_52731#玉米&&l_52732#花生","End":"数:0;登;K;{01}","Cycle":-1,"Task":11},"01收获@":{"Url":"{!nc}exchange","Post":"{ncs}&act=2103002","Msg":"direction;l_52730#小麦&&l_52731#玉米&&l_52732#花生&&name&&num","MsgOut":"direction;l_52730#小麦&&l_52731#玉米&&l_52732#花生&&name&&num","End":"登;K;不足{00}","Cycle":3,"Task":11},"02-1提交(小麦10/10分/1次)【最后一天】":{"Url":"{!nc}exchange","Post":"{ncs}&act=2103003&id=1","Note":"[] = ok","Msg":"direction;pkg??;pkg","MsgOut":"direction;pkg??;pkg","End":"不{02-2};登","Cycle":-1,"Task":11},"02-2提交(玉米10/10分/1次)@":{"Url":"{!nc}exchange","Post":"{ncs}&act=2103003&id=2","Msg":"direction;pkg??;pkg","MsgOut":"direction;pkg??;pkg","End":"不{02-3};登","Cycle":-1,"Task":11},"02-3提交(花生10/10分/1次)@":{"Url":"{!nc}exchange","Post":"{ncs}&act=2103003&id=3","Msg":"direction;pkg??;pkg","MsgOut":"direction;pkg??;pkg","End":"不;登","Cycle":-1,"Task":11},"03兑礼包":{"Url":"{!nc}exchange","Post":"{ncs}&act=2103004&id=4","Note":"id=1~4  需积分 25/48/108/215","Msg":"direction;pkg??;pkg","MsgOut":"direction;pkg??;pkg","End":"不;登","Task":11},"04 VIP":{"Url":"{!nc}exchange","Post":"{ncs}&act=2103005&id=2","Msg":"direction;pkg??;pkg","MsgOut":"direction;pkg??;pkg","End":"不;登","Task":11}}}